carla_birdeye_view
