Metadata-Version: 2.1
Name: carla-birdeye-view
Version: 1.1.1
Summary: Bird-eye's view for CARLA simulator
Home-page: https://github.com/deepsense-ai/carla-birdeye-view
Author: Michał Martyniak
Author-email: michal.martyniak@linux.pl
License: MIT
Keywords: CARLA,birdview,bird-eye's view,Reinforcement Learning,RL
Platform: UNKNOWN
Classifier: License :: OSI Approved :: MIT License
Classifier: Intended Audience :: Developers
Classifier: Intended Audience :: Science/Research
Classifier: Programming Language :: Python :: 3
Classifier: Programming Language :: Python :: 3.6
Classifier: Programming Language :: Python :: 3.7
Classifier: Programming Language :: Python :: 3.8
